jsrope/__about__.py
jsrope/__init__.py
jsrope/django.py
jsrope/flask.py
jsrope/jsrope.py
jsrope/util.py
JSRope-0.1.3.dist-info/LICENSE
JSRope-0.1.3.dist-info/METADATA
JSRope-0.1.3.dist-info/WHEEL
JSRope-0.1.3.dist-info/top_level.txt
JSRope-0.1.3.dist-info/RECORD
