Metadata-Version: 2.1
Name: JSRope
Version: 0.1.3
Summary: You don't want to write JavaScript? Me, too. But, Let me handle it with Python.
Home-page: https://github.com/delta114514/JSRope
Author: Yamato Nagata
Author-email: chickenwingswillfly@gmail.com
License: MIT
Platform: any
Classifier: Development Status :: 4 - Beta
Classifier: Environment :: Other Environment
Classifier: Environment :: Web Environment
Classifier: Intended Audience :: Developers
Classifier: License :: OSI Approved :: MIT License
Classifier: Operating System :: OS Independent
Classifier: Programming Language :: Python :: 3
Classifier: Programming Language :: Python
Classifier: Topic :: Software Development :: Libraries :: Python Modules
Requires-Dist: jsbeautifier
